main.py
mseep_geeknews_mcp_server-0.1.3.dist-info/licenses/LICENSE
mseep_geeknews_mcp_server-0.1.3.dist-info/METADATA
mseep_geeknews_mcp_server-0.1.3.dist-info/WHEEL
mseep_geeknews_mcp_server-0.1.3.dist-info/entry_points.txt
mseep_geeknews_mcp_server-0.1.3.dist-info/top_level.txt
mseep_geeknews_mcp_server-0.1.3.dist-info/RECORD
