Metadata-Version: 2.4
Name: mseep-geeknews-mcp-server
Version: 0.1.3
Summary: Add your description here
Author-email: mseep <support@skydeck.ai>
Requires-Python: >=3.12
License-File: LICENSE
Requires-Dist: beautifulsoup4>=4.13.3
Requires-Dist: mcp[cli]>=1.6.0
Requires-Dist: requests>=2.32.3
Dynamic: license-file
